makepy/__init__.py
makepy/__main__.py
makepy/_datafiles.py
makepy/_makefiles.py
makepy/_templates.py
makepy/argparse.py
makepy/cli.py
makepy/commands.py
makepy/config.py
makepy/mainlog.py
makepy/shell.py
makepy/tox.py
makepy-0.0.26.dist-info/LICENSE.txt
makepy-0.0.26.dist-info/METADATA
makepy-0.0.26.dist-info/RECORD
makepy-0.0.26.dist-info/WHEEL
makepy-0.0.26.dist-info/entry_points.txt
makepy-0.0.26.dist-info/top_level.txt
