Metadata-Version: 2.1
Name: makepy
Version: 0.0.26
Summary: makepy: Handsfree Python Module Programming
Home-page: https://github.com/ubunatic/makepy
Author: Uwe Jugel
Author-email: uwe.jugel@gmail.com
License: MIT
Project-URL: Funding, https://github.com/ubunatic/makepy
Project-URL: Documentation, https://github.com/ubunatic/makepy
Project-URL: Bug Reports, https://github.com/ubunatic/makepy/issues
Project-URL: Say Thanks!, https://saythanks.io/to/ubunatic
Project-URL: Source, https://github.com/ubunatic/makepy
Keywords: argparse,logging,structlog,cli,arguments,ArgumentParser,enhancement,automation,tox,testing
Platform: UNKNOWN
Classifier: Programming Language :: Python :: 3.6
Classifier: License :: OSI Approved :: MIT License
Classifier: Programming Language :: Python :: 3.4
Classifier: Programming Language :: Python :: 3.3
Classifier: Programming Language :: Python :: 3.5
Classifier: Development Status :: 4 - Beta
Classifier: Intended Audience :: Developers
Classifier: Topic :: Software Development :: Libraries
Classifier: Programming Language :: Python :: 2
Classifier: Programming Language :: Python :: 3
Classifier: Programming Language :: Python :: 2.6
Classifier: Programming Language :: Python :: 2.7
Classifier: Programming Language :: Python :: 2.5
Requires-Python: >=2.5
Provides-Extra: dev
Requires-Dist: typing
Requires-Dist: future
Requires-Dist: argparse
Requires-Dist: configparser
Provides-Extra: dev
Requires-Dist: pytest; extra == 'dev'
Requires-Dist: flake8; extra == 'dev'
Requires-Dist: twine; extra == 'dev'
Requires-Dist: pasteurize; extra == 'dev'
